spconv.libs/libgomp-a34b3233.so.1.0.0
spconv-2.3.8.dist-info/METADATA
spconv-2.3.8.dist-info/RECORD
spconv-2.3.8.dist-info/top_level.txt
spconv-2.3.8.dist-info/WHEEL
spconv-2.3.8.dist-info/LICENSE
spconv/test_utils.py
spconv/algo.py
spconv/tools.py
spconv/__init__.py
spconv/debug_utils.py
spconv/constants.py
spconv/algocore.py
spconv/core_cc.cpython-311-x86_64-linux-gnu.so
spconv/core.py
spconv/build.py
spconv/cppconstants.py
spconv/__version__.py
spconv/csrc/__init__.py
spconv/csrc/sparse/inference.py
spconv/csrc/sparse/alloc.py
spconv/csrc/sparse/maxpool.py
spconv/csrc/sparse/__init__.py
spconv/csrc/sparse/pointops.py
spconv/csrc/sparse/indices.py
spconv/csrc/sparse/cpu_core.py
spconv/csrc/sparse/all.py
spconv/csrc/sparse/convops.py
spconv/csrc/sparse/gather.py
spconv/csrc/hash/__init__.py
spconv/csrc/hash/core.py
spconv/csrc/utils/launch.py
spconv/csrc/utils/boxops.py
spconv/csrc/utils/__init__.py
spconv/csrc/utils/pcc.py
spconv/gencode/__init__.py
spconv/gencode/__main__.py
spconv/utils/__init__.py
spconv/core_cc/__init__.pyi
spconv/core_cc/csrc/__init__.pyi
spconv/core_cc/csrc/sparse/alloc.pyi
spconv/core_cc/csrc/sparse/inference.pyi
spconv/core_cc/csrc/sparse/__init__.pyi
spconv/core_cc/csrc/sparse/all/ops_cpu2d.pyi
spconv/core_cc/csrc/sparse/all/__init__.pyi
spconv/core_cc/csrc/sparse/all/ops_cpu1d.pyi
spconv/core_cc/csrc/sparse/all/ops_cpu3d.pyi
spconv/core_cc/csrc/sparse/all/ops_cpu4d.pyi
spconv/core_cc/csrc/sparse/convops/gemmops.pyi
spconv/core_cc/csrc/sparse/convops/spops.pyi
spconv/core_cc/csrc/sparse/convops/__init__.pyi
spconv/core_cc/csrc/sparse/convops/convops.pyi
spconv/core_cc/csrc/hash/core.pyi
spconv/core_cc/csrc/hash/__init__.pyi
spconv/core_cc/csrc/utils/boxops.pyi
spconv/core_cc/csrc/utils/pcc.pyi
spconv/core_cc/csrc/utils/__init__.pyi
spconv/core_cc/cumm/common.pyi
spconv/core_cc/cumm/__init__.pyi
spconv/pytorch/modules.py
spconv/pytorch/conv.py
spconv/pytorch/functional.py
spconv/pytorch/interpreter.py
spconv/pytorch/identity.py
spconv/pytorch/tables.py
spconv/pytorch/ops.py
spconv/pytorch/cppcore.py
spconv/pytorch/spatial.py
